{"chunk_definitions":[{"chunk_id":"cmoi486ab7i1j","chunk_label":"unnamed-chunk-1","document_id":"C0ADB462","expansion_state":0,"options":{"engine":"r","include":false,"label":"unnamed-chunk-1","message":false,"paged.print":false,"warning":false},"row":16,"row_count":1,"visible":true},{"chunk_id":"c7av92xx0hzck","chunk_label":"unnamed-chunk-3","document_id":"C0ADB462","expansion_state":0,"options":{"engine":"r","label":"unnamed-chunk-2"},"row":147,"row_count":1,"visible":true}],"doc_write_time":1528711156}